error_analysis/__init__.py
error_analysis/constants.py
error_analysis/debug.py
error_analysis/evar.py
error_analysis/operators.py
error_analysis/options.py
error_analysis/plot.py
error_analysis/regression.py
error_analysis/tools.py
error_analysis/variable.py
error_analysis-0.1.2.dist-info/LICENSE
error_analysis-0.1.2.dist-info/METADATA
error_analysis-0.1.2.dist-info/WHEEL
error_analysis-0.1.2.dist-info/top_level.txt
error_analysis-0.1.2.dist-info/RECORD
