Metadata-Version: 2.1
Name: error-analysis
Version: 0.1.2
Summary: Small library for easier propagation of uncertainty
Home-page: https://github.com/finnschwall/ErrorAnalysis
Author: Finn
Author-email: finn1@web.de
License: Apache License 2.0 
Platform: UNKNOWN
Classifier: Programming Language :: Python :: 3
Classifier: Operating System :: OS Independent
Requires-Dist: numpy
Requires-Dist: scipy
Requires-Dist: sympy
Requires-Dist: matplotlib
Requires-Dist: varname
